LICENSE
README.md
setup.py
tsaopy/__init__.py
tsaopy/auxinit.py
tsaopy/events.py
tsaopy/models.py
tsaopy.egg-info/PKG-INFO
tsaopy.egg-info/SOURCES.txt
tsaopy.egg-info/dependency_links.txt
tsaopy.egg-info/requires.txt
tsaopy.egg-info/top_level.txt