Metadata-Version: 2.1
Name: tsaopy
Version: 0.0.4a0
Summary: Time Series by Anharmonic Oscillators is a Python library designed to analize time series by modelling them as anharmonic oscillators.
Home-page: https://tsaopy.github.io/
Author: Sofia A. Scozziero
Author-email: sgscozziero@gmail.com
Classifier: Programming Language :: Python :: 3
Classifier: License :: OSI Approved :: GNU General Public License v3 (GPLv3)
Classifier: Operating System :: POSIX :: Linux
License-File: LICENSE
